.codecov.yml
.coveragerc
.gitignore
.pre-commit-config.yaml
.readthedocs.yml
LICENSE
MANIFEST.in
README.rst
azure-pipelines.yml
codecov.yml
conftest.py
environment.yml
pyproject.toml
setup.cfg
setup.py
.circleci/config.yml
.github/workflows/build-wheels.yml
benchmarks/__init__.py
benchmarks/bench_rbfsampler_fastfood.py
benchmarks/_bench/__init__.py
benchmarks/_bench/eigenpro_plot_mnist.py
benchmarks/_bench/eigenpro_plot_noisy_mnist.py
benchmarks/_bench/eigenpro_plot_synthetic.py
benchmarks/_bench/robust_plot_synthetic.py
doc/Makefile
doc/api.rst
doc/changelog.rst
doc/conf.py
doc/contributing.rst
doc/docs.md
doc/index.rst
doc/install.rst
doc/make.bat
doc/user_guide.rst
doc/_static/css/project-template.css
doc/_static/js/copybutton.js
doc/_templates/class.rst
doc/_templates/function.rst
doc/_templates/numpydoc_docstring.py
doc/images/eigenpro_mnist.png
doc/images/eigenpro_mnist_noisy.png
doc/images/eigenpro_synthetic.png
doc/images/robust_def_outliers.png
doc/images/robust_plot_regression.png
doc/modules/cluster.rst
doc/modules/eigenpro.rst
doc/modules/kernel_approximation.rst
doc/modules/robust.rst
examples/README.txt
examples/plot_clara_digits.py
examples/plot_commonnn.py
examples/plot_kmedoids.py
examples/plot_robust_classification_toy.py
examples/plot_robust_regression_toy.py
examples/cluster/README.txt
examples/cluster/plot_clustering.py
examples/cluster/plot_commonnn_data_sets.py
examples/cluster/plot_kmedoids_digits.py
examples/eigenpro/README.txt
examples/eigenpro/plot_eigenpro_synthetic.py
examples/kernel_approximation/README.txt
examples/kernel_approximation/plot_digits_classification_fastfood.py
examples/kernel_approximation/plot_kernel_approximation.py
examples/robust/README.txt
examples/robust/plot_robust_classification_diabete.py
examples/robust/plot_robust_regression_california_houses.py
sklearn_extra/__init__.py
sklearn_extra/_version.py
sklearn_extra/cluster/__init__.py
sklearn_extra/cluster/_commonnn.py
sklearn_extra/cluster/_commonnn_inner.cpp
sklearn_kmedoids_on_string.egg-info/PKG-INFO
sklearn_kmedoids_on_string.egg-info/SOURCES.txt
sklearn_kmedoids_on_string.egg-info/dependency_links.txt
sklearn_kmedoids_on_string.egg-info/not-zip-safe
sklearn_kmedoids_on_string.egg-info/requires.txt
sklearn_kmedoids_on_string.egg-info/top_level.txt